xyz_util/__init__.py
xyz_util/asyncioutils.py
xyz_util/cmdutils.py
xyz_util/crawlutils.py
xyz_util/cryptutils.py
xyz_util/datautils.py
xyz_util/dateutils.py
xyz_util/dbutils.py
xyz_util/elasearchutils.py
xyz_util/excelutils.py
xyz_util/fc3.py
xyz_util/formutils.py
xyz_util/importutils.py
xyz_util/mediautils.py
xyz_util/modelutils.py
xyz_util/mongoutils.py
xyz_util/pandasutils.py
xyz_util/pdfutils.py
xyz_util/sqlalchemyutils.py
xyz_util/statutils.py
xyz_util/textutils.py
xyz_util/transferutils.py
xyz_util/validators.py
xyz_util/views.py
xyz_util/widgetutils.py
xyz_util-1.4.3.dist-info/METADATA
xyz_util-1.4.3.dist-info/WHEEL
xyz_util-1.4.3.dist-info/top_level.txt
xyz_util-1.4.3.dist-info/RECORD
